[
  {
    "Author": "Jukka, RedAsteroid(本地化)",
    "Name": "NecroLens",
    "InternalName": "NecroLens",
    "Punchline": "一个真正的死灵术士总是对深层迷宫了如指掌…… 而其他人只是在使用高科技！\n(在线安装 Only)",
    "AssemblyVersion": "1.0.3.6",
    "Description": "深层迷宫小帮手，提供怪物的引战、视觉范围以及其他一切的雷达。\n继续更正了正统优雷卡中部分错误的引战范围显示。\nCN6.38 闲鱼小店倒卖死妈，买的也死妈。",
    "ApplicableVersion": "any",
    "DalamudApiLevel": 8,
    "IconUrl": "https://github.com/Jukkales/NecroLens/raw/main/icon.png",
    "DownloadLinkInstall": "https://github.com/RedAsteroid/NecroLens/releases/download/3/latest.zip",
    "DownloadLinkUpdate": "https://github.com/RedAsteroid/NecroLens/releases/download/3/latest.zip",
  },
  {
    "Author": "Chalkos",
    "Name": "Marketbuddy",
    "InternalName": "Marketbuddy",
    "Punchline": "更少的点击，更多的金币!",
    "AssemblyVersion": "0.2.2.16",
    "Description": "协助您进行日复一日的市场操作\nCN6.31 本地化 By RedAsteroid",
    "ApplicableVersion": "any",
    "DalamudApiLevel": 8,
    "IconUrl": " null",
    "DownloadLinkInstall": "https://github.com/RedAsteroid/DalamudPlugins/raw/main/Plugins/Marketbuddy/latest.zip",
    "DownloadLinkUpdate": "https://github.com/RedAsteroid/DalamudPlugins/raw/main/Plugins/Marketbuddy/latest.zip",
  },
  {
    "Author": "Asteria Nocturna",
    "Name": "Divination.AetheryteLinkInChat",
    "InternalName": "AetheryteLinkInChat",
    "Punchline": "为怪物狩猎进行快速传送",
    "AssemblyVersion": "0.1.0.1255",
    "Description": "将一个传送到最近水晶的链接添加到含有地图标记的聊天中。",
    "ApplicableVersion": "any",
    "DalamudApiLevel": 8,
    "IconUrl": " null",
    "DownloadLinkInstall": "https://github.com/RedAsteroid/DalamudPlugins/raw/main/Plugins/AetheryteLinkInChat/AttheryteLinkInChat0.1.0.1255.zip",
    "DownloadLinkUpdate": "https://github.com/RedAsteroid/DalamudPlugins/raw/main/Plugins/AetheryteLinkInChat/AttheryteLinkInChat0.1.0.1255.zip",
  },
  {
    "Author": "NightmareXIV, RedAsteroid(翻译)",
    "Name": "TextAdvance",
    "InternalName": "TextAdvance",
    "Punchline": "自动跳过对话框以及确认跳过过场动画，对副职升级十分有效。需要在每次登陆时输入 /at 命令才能启用。\n(在线安装 Only)",
    "AssemblyVersion": "3.0.0.8",
    "Description": "",
    "ApplicableVersion": "any",
    "DalamudApiLevel": 8,
    "IconUrl": "https://raw.githubusercontent.com/Eternita-S/MyDalamudPlugins/main/TextAdvance/icon.png",
    "DownloadLinkInstall": "https://github.com/RedAsteroid/TextAdvance/releases/download/1/latest.zip",
    "DownloadLinkUpdate": "https://github.com/RedAsteroid/TextAdvance/releases/download/1/latest.zip",
  },
  {
    "Author": "NightmareXIV",
    "Name": "HuntTrainAssistant",
    "InternalName": "HuntTrainAssistant",
    "Punchline": "[beta] 狩猎车辅助工具",
    "AssemblyVersion": "1.0.0.2",
    "Description": "为狩猎车提供实用的工具，例如：高亮车头的信息并屏蔽其他所有的聊天内容、自动打开车头发送的坐标链接以及自动传送到车头发送的目的地。",
    "ApplicableVersion": "any",
    "DalamudApiLevel": 8,
    "IconUrl": "https://raw.githubusercontent.com/NightmareXIV/MyDalamudPlugins/main/icons/HuntTrainassist.png",
    "DownloadLinkInstall": "https://github.com/RedAsteroid/HuntTrainAssistant/releases/download/1/HuntTrainAssistant.zip",
    "DownloadLinkUpdate": "https://github.com/RedAsteroid/HuntTrainAssistant/releases/download/1/HuntTrainAssistant.zip",
  }
 ]
